emojis/__init__.py
emojis/__main__.py
randomemojis-0.3.dist-info/LICENSE
randomemojis-0.3.dist-info/METADATA
randomemojis-0.3.dist-info/WHEEL
randomemojis-0.3.dist-info/entry_points.txt
randomemojis-0.3.dist-info/top_level.txt
randomemojis-0.3.dist-info/RECORD
